even_more_itertools/__init__.py
even_more_itertools/itertools.py
even_more_itertools-0.0.1.dist-info/DESCRIPTION.rst
even_more_itertools-0.0.1.dist-info/METADATA
even_more_itertools-0.0.1.dist-info/RECORD
even_more_itertools-0.0.1.dist-info/WHEEL
even_more_itertools-0.0.1.dist-info/metadata.json
even_more_itertools-0.0.1.dist-info/top_level.txt
