Metadata-Version: 2.0
Name: even-more-itertools
Version: 0.0.1
Summary: Collection of even more itertools.
Home-page: https://github.com/nvie/even-more-itertools
Author: Vincent Driessen
Author-email: me@nvie.com
License: UNKNOWN
Platform: any
Requires-Dist: more-itertools
